setup.py
Druvesh/Binomialdistribution.py
Druvesh/Gaussiandistribution.py
Druvesh/Generaldistribution.py
Druvesh/__init__.py
Druvesh.egg-info/PKG-INFO
Druvesh.egg-info/SOURCES.txt
Druvesh.egg-info/dependency_links.txt
Druvesh.egg-info/not-zip-safe
Druvesh.egg-info/top_level.txt